indonesia_shipping/ShippingService.py
indonesia_shipping/ShippingServiceFactory.py
indonesia_shipping/SicepatService.py
indonesia_shipping/__init__.py
indonesia_shipping/test_sicepat_service.py
indonesia_shipping_service-0.1.7.dist-info/LICENSE
indonesia_shipping_service-0.1.7.dist-info/METADATA
indonesia_shipping_service-0.1.7.dist-info/WHEEL
indonesia_shipping_service-0.1.7.dist-info/top_level.txt
indonesia_shipping_service-0.1.7.dist-info/RECORD
