Metadata-Version: 2.1
Name: indonesia-shipping-service
Version: 0.1.7
Summary: Indonesia Shipping Service
Home-page: https://github.com/xhijack/indonesia-shipping-service
Author: ramdani muksin
Author-email: ramd4ni@gmail.com
License: UNKNOWN
Platform: UNKNOWN
Classifier: Programming Language :: Python :: 3
Classifier: License :: OSI Approved :: MIT License
Classifier: Operating System :: OS Independent
Requires-Python: >=3.6
